Workbook
Name ExpenseTrackerTotal: 'Expense Tracker'!$F$156

Sheet Read Me
A1: GigMath Pro Kit
A3: Educational spreadsheet for a US gig driver or 1099 freelancer. Not tax, legal, or financial advice.
A4: IRS business standard mileage rate for 2026, from irs.gov/tax-professionals/standard-mileage-rates:
A5: 72.5 cents per mile for January 1 through June 30, 2026 (Notice 2026-10).
A6: 76 cents per mile for July 1 through December 31, 2026 (Announcement 2026-11).
A7: Change the two rate cells on Settings if the IRS revises them. Do not treat those rates as cash the app paid you.
A8: Standard mileage replaces gas, oil, insurance, registration, repairs, lease payments, and depreciation. Do not also deduct those.
A9: Business parking, tolls, and the business percentage of car-loan interest can be separate. See IRS Publication 463.
A10: Commuting is not a business mile. Publication 463 treats the trip from home to the first stop, and from the last stop home, as commuting unless a listed exception applies.
A11: Self-employment tax follows Schedule SE: profit × 92.35%. If that result is under $400, the sheet shows no self-employment tax. Social Security is 12.4% up to the 2026 $184,500 wage base. Medicare is 2.9% with no cap.
A12: Half of self-employment tax is subtracted before the income-tax estimate. Additional Medicare Tax (Form 8959) and the qualified business income deduction are not calculated.
A13: The income-tax rate cell is yours. GigMath does not supply an official rate.
... A18: This workbook is the Pro Kit product. It is not a public download.

Sheet Settings
A1: Settings you can edit
A3: Setting | B3: Value | C3: Source or instruction
A4: Business mileage rate, Jan 1–Jun 30, 2026 | B4: 0.725 | C4: IRS Notice 2026-10. Edit only if the IRS changes it.
A5: Business mileage rate, Jul 1–Dec 31, 2026 | B5: 0.76 | C5: IRS Announcement 2026-11. Edit only if the IRS changes it.
A6: Your estimated federal income-tax rate | C6: Type a decimal such as 0.12 or 0.22. Leave blank to estimate self-employment tax only.
A7: 2026 Social Security wage base | B7: 184500 | C7: Printed on 2026 Schedule SE. Edit only if the IRS figure differs.
A9: Green cells are inputs. Other sheets read them. Do not type over formulas on the log sheets.

Sheet Mileage Log
A1: Mileage log
A2: Enter the date, odometer readings, destination, and business purpose. Miles and the deduction calculate themselves. Leave commuting trips off this sheet. The rate switches on July 1, 2026 using Settings.
K3: Total business miles | L3: =SUM(E5:E204)
A4: Date | B4: Platform | C4: Start odometer | D4: End odometer | E4: Miles | F4: Destination | G4: Business purpose | H4: IRS rate | I4: Deduction | K4: Total standard-mileage deduction | L4: =SUM(I5:I204)
E5: =IF(OR(C5="",D5=""),"",D5-C5) | H5: =IF(A5="","",IF(A5<DATE(2026,7,1),Settings!$B$4,Settings!$B$5)) | I5: =IF(OR(E5="",H5=""),"",E5*H5)
E6: =IF(OR(C6="",D6=""),"",D6-C6) | H6: =IF(A6="","",IF(A6<DATE(2026,7,1),Settings!$B$4,Settings!$B$5)) | I6: =IF(OR(E6="",H6=""),"",E6*H6)
E7: =IF(OR(C7="",D7=""),"",D7-C7) | H7: =IF(A7="","",IF(A7<DATE(2026,7,1),Settings!$B$4,Settings!$B$5)) | I7: =IF(OR(E7="",H7=""),"",E7*H7)
E8: =IF(OR(C8="",D8=""),"",D8-C8) | H8: =IF(A8="","",IF(A8<DATE(2026,7,1),Settings!$B$4,Settings!$B$5)) | I8: =IF(OR(E8="",H8=""),"",E8*H8)
E9: =IF(OR(C9="",D9=""),"",D9-C9) | H9: =IF(A9="","",IF(A9<DATE(2026,7,1),Settings!$B$4,Settings!$B$5)) | I9: =IF(OR(E9="",H9=""),"",E9*H9)
E10: =IF(OR(C10="",D10=""),"",D10-C10) | H10: =IF(A10="","",IF(A10<DATE(2026,7,1),Settings!$B$4,Settings!$B$5)) | I10: =IF(OR(E10="",H10=""),"",E10*H10)
E11: =IF(OR(C11="",D11=""),"",D11-C11) | H11: =IF(A11="","",IF(A11<DATE(2026,7,1),Settings!$B$4,Settings!$B$5)) | I11: =IF(OR(E11="",H11=""),"",E11*H11)
E12: =IF(OR(C12="",D12=""),"",D12-C12) | H12: =IF(A12="","",IF(A12<DATE(2026,7,1),Settings!$B$4,Settings!$B$5)) | I12: =IF(OR(E12="",H12=""),"",E12*H12)
E13: =IF(OR(C13="",D13=""),"",D13-C13) | H13: =IF(A13="","",IF(A13<DATE(2026,7,1),Settings!$B$4,Settings!$B$5)) | I13: =IF(OR(E13="",H13=""),"",E13*H13)
E14: =IF(OR(C14="",D14=""),"",D14-C14) | H14: =IF(A14="","",IF(A14<DATE(2026,7,1),Settings!$B$4,Settings!$B$5)) | I14: =IF(OR(E14="",H14=""),"",E14*H14)
E15: =IF(OR(C15="",D15=""),"",D15-C15) | H15: =IF(A15="","",IF(A15<DATE(2026,7,1),Settings!$B$4,Settings!$B$5)) | I15: =IF(OR(E15="",H15=""),"",E15*H15)
E16: =IF(OR(C16="",D16=""),"",D16-C16) | H16: =IF(A16="","",IF(A16<DATE(2026,7,1),Settings!$B$4,Settings!$B$5)) | I16: =IF(OR(E16="",H16=""),"",E16*H16)
... E204: =IF(OR(C204="",D204=""),"",D204-C204) | H204: =IF(A204="","",IF(A204<DATE(2026,7,1),Settings!$B$4,Settings!$B$5)) | I204: =IF(OR(E204="",H204=""),"",E204*H204)

Sheet Weekly Earnings
A1: Weekly earnings
A2: One row per platform per week. Cash left subtracts fees and fuel you type. It does not subtract the mileage-rate estimate. That estimate is a tax figure, and only if you use the standard mileage method.
A4: Week starting | B4: Platform | C4: Pay | D4: Tips | E4: Fees | F4: Business miles | G4: Online hours | H4: Fuel paid | I4: Gross | J4: Mileage deduction estimate | K4: Cash left | L4: Cash per online hour
I5: =IF(COUNT(C5:D5)=0,"",C5+D5) | J5: =IF(OR(A5="",F5=""),"",F5*IF(A5<DATE(2026,7,1),Settings!$B$4,Settings!$B$5)) | K5: =IF(I5="","",I5-SUM(E5,H5)) | L5: =IF(OR(K5="",G5="",G5=0),"",K5/G5)
I6: =IF(COUNT(C6:D6)=0,"",C6+D6) | J6: =IF(OR(A6="",F6=""),"",F6*IF(A6<DATE(2026,7,1),Settings!$B$4,Settings!$B$5)) | K6: =IF(I6="","",I6-SUM(E6,H6)) | L6: =IF(OR(K6="",G6="",G6=0),"",K6/G6)
I7: =IF(COUNT(C7:D7)=0,"",C7+D7) | J7: =IF(OR(A7="",F7=""),"",F7*IF(A7<DATE(2026,7,1),Settings!$B$4,Settings!$B$5)) | K7: =IF(I7="","",I7-SUM(E7,H7)) | L7: =IF(OR(K7="",G7="",G7=0),"",K7/G7)
I8: =IF(COUNT(C8:D8)=0,"",C8+D8) | J8: =IF(OR(A8="",F8=""),"",F8*IF(A8<DATE(2026,7,1),Settings!$B$4,Settings!$B$5)) | K8: =IF(I8="","",I8-SUM(E8,H8)) | L8: =IF(OR(K8="",G8="",G8=0),"",K8/G8)
I9: =IF(COUNT(C9:D9)=0,"",C9+D9) | J9: =IF(OR(A9="",F9=""),"",F9*IF(A9<DATE(2026,7,1),Settings!$B$4,Settings!$B$5)) | K9: =IF(I9="","",I9-SUM(E9,H9)) | L9: =IF(OR(K9="",G9="",G9=0),"",K9/G9)
I10: =IF(COUNT(C10:D10)=0,"",C10+D10) | J10: =IF(OR(A10="",F10=""),"",F10*IF(A10<DATE(2026,7,1),Settings!$B$4,Settings!$B$5)) | K10: =IF(I10="","",I10-SUM(E10,H10)) | L10: =IF(OR(K10="",G10="",G10=0),"",K10/G10)
I11: =IF(COUNT(C11:D11)=0,"",C11+D11) | J11: =IF(OR(A11="",F11=""),"",F11*IF(A11<DATE(2026,7,1),Settings!$B$4,Settings!$B$5)) | K11: =IF(I11="","",I11-SUM(E11,H11)) | L11: =IF(OR(K11="",G11="",G11=0),"",K11/G11)
I12: =IF(COUNT(C12:D12)=0,"",C12+D12) | J12: =IF(OR(A12="",F12=""),"",F12*IF(A12<DATE(2026,7,1),Settings!$B$4,Settings!$B$5)) | K12: =IF(I12="","",I12-SUM(E12,H12)) | L12: =IF(OR(K12="",G12="",G12=0),"",K12/G12)
I13: =IF(COUNT(C13:D13)=0,"",C13+D13) | J13: =IF(OR(A13="",F13=""),"",F13*IF(A13<DATE(2026,7,1),Settings!$B$4,Settings!$B$5)) | K13: =IF(I13="","",I13-SUM(E13,H13)) | L13: =IF(OR(K13="",G13="",G13=0),"",K13/G13)
I14: =IF(COUNT(C14:D14)=0,"",C14+D14) | J14: =IF(OR(A14="",F14=""),"",F14*IF(A14<DATE(2026,7,1),Settings!$B$4,Settings!$B$5)) | K14: =IF(I14="","",I14-SUM(E14,H14)) | L14: =IF(OR(K14="",G14="",G14=0),"",K14/G14)
I15: =IF(COUNT(C15:D15)=0,"",C15+D15) | J15: =IF(OR(A15="",F15=""),"",F15*IF(A15<DATE(2026,7,1),Settings!$B$4,Settings!$B$5)) | K15: =IF(I15="","",I15-SUM(E15,H15)) | L15: =IF(OR(K15="",G15="",G15=0),"",K15/G15)
I16: =IF(COUNT(C16:D16)=0,"",C16+D16) | J16: =IF(OR(A16="",F16=""),"",F16*IF(A16<DATE(2026,7,1),Settings!$B$4,Settings!$B$5)) | K16: =IF(I16="","",I16-SUM(E16,H16)) | L16: =IF(OR(K16="",G16="",G16=0),"",K16/G16)
... I108: =IF(COUNT(C108:D108)=0,"",C108+D108) | J108: =IF(OR(A108="",F108=""),"",F108*IF(A108<DATE(2026,7,1),Settings!$B$4,Settings!$B$5)) | K108: =IF(I108="","",I108-SUM(E108,H108)) | L108: =IF(OR(K108="",G108="",G108=0),"",K108/G108)
A110: Totals | C110: =SUM(C5:C108) | D110: =SUM(D5:D108) | E110: =SUM(E5:E108) | F110: =SUM(F5:F108) | G110: =SUM(G5:G108) | H110: =SUM(H5:H108) | I110: =SUM(I5:I108) | J110: =SUM(J5:J108) | K110: =SUM(K5:K108) | L110: =IF(G110=0,"",K110/G110)

Sheet Expense Tracker
A1: Expense tracker
A2: Parking, tolls, the business percentage of car-loan interest, and other non-mileage costs. If you use the standard mileage method, do not list gas, insurance, repairs, or registration here — those are inside the IRS rate. If you use actual costs, record fuel either here or on Weekly Earnings, not both. Business use of 100% is 1.
A4: Date | B4: Category | C4: Description | D4: Amount | E4: Business use (1 = 100%) | F4: Deductible amount
F5: =IF(OR(D5="",E5=""),"",D5*E5)
F6: =IF(OR(D6="",E6=""),"",D6*E6)
F7: =IF(OR(D7="",E7=""),"",D7*E7)
F8: =IF(OR(D8="",E8=""),"",D8*E8)
F9: =IF(OR(D9="",E9=""),"",D9*E9)
F10: =IF(OR(D10="",E10=""),"",D10*E10)
F11: =IF(OR(D11="",E11=""),"",D11*E11)
F12: =IF(OR(D12="",E12=""),"",D12*E12)
F13: =IF(OR(D13="",E13=""),"",D13*E13)
F14: =IF(OR(D14="",E14=""),"",D14*E14)
F15: =IF(OR(D15="",E15=""),"",D15*E15)
F16: =IF(OR(D16="",E16=""),"",D16*E16)
... F154: =IF(OR(D154="",E154=""),"",D154*E154)
A156: Total deductible | F156: =SUM(F5:F154)

Sheet Quarterly Tax
A1: Quarterly tax estimator
A2: Pick a car method. Standard subtracts the mileage-log deduction and does not subtract weekly fuel. Actual subtracts weekly fuel and does not subtract the mileage rate. Expense Tracker is subtracted either way, so do not duplicate a cost. This is a federal estimate, not a filed Form 1040-ES.
A4: Car method (type standard or actual) | B4: standard
A5: W-2 Social Security wages (Form W-2, boxes 3 and 7) | B5: 0
A7: Gross pay + tips | B7: ='Weekly Earnings'!C110+'Weekly Earnings'!D110
A8: Fees | B8: ='Weekly Earnings'!E110
A9: Mileage deduction (standard method) | B9: ='Mileage Log'!L4 | C9: From the Mileage Log total. Weekly miles are only an estimate until you log the trips.
A10: Fuel typed on Weekly Earnings (actual method) | B10: ='Weekly Earnings'!H110
A11: Other deductible expenses | B11: =ExpenseTrackerTotal
A12: Net profit used for this estimate | B12: =IF(B4="actual",B7-B8-B10-B11,B7-B8-B9-B11)
A14: Net earnings (profit × 92.35%) | B14: =B12*0.9235
A15: Self-employment tax applies | B15: =IF(B14<400,"No — under $400","Yes")
A16: Social Security room left under the wage base | B16: =MAX(0,Settings!B7-B5)
A17: Social Security portion (12.4%) | B17: =IF(B14<400,0,MIN(B14,B16)*0.124)
A18: Medicare portion (2.9%) | B18: =IF(B14<400,0,B14*0.029)
A19: Self-employment tax | B19: =B17+B18
A20: Deduction for half of self-employment tax | B20: =B19*0.5
A21: Income-tax set-aside at your Settings rate | B21: =IF(Settings!B6="",0,MAX(0,B12-B20)*Settings!B6)
A22: Federal set-aside estimate | B22: =B19+B21
A23: Equal amount for each of 4 due dates | B23: =B22/4
A25: Form 1040-ES due dates for calendar year 2026
A26: Payment | B26: Due date | C26: Equal estimate
A27: 1 | B27: 2026-04-15 | C27: =$B$23
A28: 2 | B28: 2026-06-15 | C28: =$B$23
A29: 3 | B29: 2026-09-15 | C29: =$B$23
A30: 4 | B30: 2027-01-15 | C30: =$B$23
A32: You can skip the January 15, 2027 payment if you file the 2026 return by February 1, 2027 and pay the balance due. Equal amounts ignore the annualized method.
